

[
    {
        "id": 1,
        "nombre": "Classic Furay",
        "precio": "25.99",
        "imagen": "IMAGES/furaymaki.png"
    },
    {
        "id": 2,
        "nombre": "California Premium",
        "precio": "24.99",
        "imagen": "IMAGES/makicalifornia.png"
    },
    {
        "id": 3,
        "nombre": "Gunkan Deluxe",
        "precio": "22.99",
        "imagen": "IMAGES/gunkans.png"
    },
    {
        "id": 4,
        "nombre": "Traditional Hoso Maki ",
        "precio": "30.99",
        "imagen": "IMAGES/hosomaki.png"
    },
    {
        "id": 5,
        "nombre": "Nigiri Selection",
        "precio": "42.99",
        "imagen": "IMAGES/nigiris.png"
    },
    {
        "id": 6,
        "nombre": "Especial TUMAKI",
        "precio": "47.99",
        "imagen": "IMAGES/especialmaki.png"
    },
    {
        "id": 7,
        "nombre": "Deluxe Gunkans Experience",
        "precio": "64.99",
        "imagen": "IMAGES/deluxemaki.png"
    },
    {
        "id": 8,
        "nombre": "Salmon Lover",
        "precio": "49.99",
        "imagen": "IMAGES/makisalmon.png"
    },
    {
        "id": 9,
        "nombre": "Sashimi Atun",
        "precio": "56.99",
        "imagen": "IMAGES/sashimiatun.png"
    },
    {
        "id": 10,
        "nombre": "Yakuza Maki",
        "precio": "28.99",
        "imagen": "IMAGES/yakuzamaki1.png"
    },
    {
        "id": 11,
        "nombre": "Salmon Legendary",
        "precio": "46.99",
        "imagen": "IMAGES/yakuzamaki.png"
    },
    {
        "id": 12,
        "nombre": "Selection Furay ",
        "precio": "33.99",
        "imagen": "IMAGES/furaymaki1.png"
    },
    {
        "id": 13,
        "nombre": "Sashimi Salmón",
        "precio": "59.99",
        "imagen": "IMAGES/sashimisalmon.png"
    },
    {
        "id": 14,
        "nombre": "Nigiris Mixlover",
        "precio": "49.99",
        "imagen": "IMAGES/nigiris1.png"
    }
    ]